methurator/__init__.py
methurator/cli.py
methurator/downsample.py
methurator/gt_estimator.py
methurator/plot.py
methurator/config_utils/__init__.py
methurator/config_utils/bam_utils.py
methurator/config_utils/config_formatter.py
methurator/config_utils/config_validator.py
methurator/config_utils/download_reference.py
methurator/config_utils/validation_utils.py
methurator/config_utils/verbose_utils.py
methurator/downsample_utils/__init__.py
methurator/downsample_utils/math_model.py
methurator/downsample_utils/methyldackel.py
methurator/downsample_utils/run_processing.py
methurator/downsample_utils/subsample_bam.py
methurator/downsample_utils/yaml_summary.py
methurator/gt_utils/__init__.py
methurator/gt_utils/config_validator.py
methurator/gt_utils/methyldackel.py
methurator/gt_utils/rational_function.py
methurator/gt_utils/run_estimator.py
methurator/gt_utils/yaml_summary.py
methurator/gt_utils/ztnb.py
methurator/plot_utils/__init__.py
methurator/plot_utils/plot_curve.py
methurator/plot_utils/plot_functions.py
methurator/plot_utils/plot_gtestimator.py
methurator-2.1.1.dist-info/licenses/LICENSE
methurator-2.1.1.dist-info/METADATA
methurator-2.1.1.dist-info/WHEEL
methurator-2.1.1.dist-info/entry_points.txt
methurator-2.1.1.dist-info/top_level.txt
methurator-2.1.1.dist-info/RECORD
