Metadata-Version: 2.4
Name: methurator
Version: 2.1.1
Summary: Python package designed to estimate CpGs saturation for DNA methylation sequencing data.
Author-email: Edoardo Giuili <edoardogiuili@gmail.com>
License: MIT License
Project-URL: Changelog, https://github.com/VIBTOBIlab/methurator/blob/main/CHANGELOG.md
Project-URL: Documentation, https://github.com/VIBTOBIlab/methurator/README.md
Project-URL: Issues, https://github.com/VIBTOBIlab/methurator/issues
Project-URL: Repository, https://github.com/VIBTOBIlab/methurator
Keywords: bioinformatics,biology,BSseq,methylation,RRBS
Classifier: Programming Language :: Python :: 3 :: Only
Classifier: Programming Language :: Python :: 3.10
Classifier: Programming Language :: Python :: 3.11
Classifier: Programming Language :: Python :: 3.12
Classifier: Programming Language :: Python :: 3.13
Requires-Python: <3.14,>=3.10
License-File: LICENSE
Requires-Dist: matplotlib
Requires-Dist: numpy
Requires-Dist: packaging>=24
Requires-Dist: pandas
Requires-Dist: pyfaidx
Requires-Dist: pysam
Requires-Dist: pyyaml
Requires-Dist: rich
Requires-Dist: rich-click
Requires-Dist: scipy
Requires-Dist: tqdm
Requires-Dist: plotly
Provides-Extra: dev
Requires-Dist: pytest; extra == "dev"
Requires-Dist: pytest-xdist; extra == "dev"
Dynamic: license-file
